pelican_gist/__init__.py
pelican_gist/plugin.py
pelican_gist/test_plugin.py
pelican_gist-0.3.4.dist-info/DESCRIPTION.rst
pelican_gist-0.3.4.dist-info/METADATA
pelican_gist-0.3.4.dist-info/RECORD
pelican_gist-0.3.4.dist-info/WHEEL
pelican_gist-0.3.4.dist-info/metadata.json
pelican_gist-0.3.4.dist-info/top_level.txt
