Metadata-Version: 2.0
Name: pelican-gist
Version: 0.3.4
Summary: Easily embed GitHub Gists in your Pelican articles.
Home-page: https://github.com/streeter/pelican-gist
Author: Chris Streeter
Author-email: chris@chrisstreeter.com
License: MIT
Platform: UNKNOWN
Classifier: Development Status :: 4 - Beta
Classifier: Environment :: Console
Classifier: Intended Audience :: Developers
Classifier: License :: OSI Approved :: MIT License
Classifier: Natural Language :: English
Classifier: Operating System :: OS Independent
Classifier: Programming Language :: Python
Classifier: Programming Language :: Python :: 2.6
Classifier: Programming Language :: Python :: 2.7
Classifier: Programming Language :: Python :: 3.6
Classifier: Topic :: Internet :: WWW/HTTP
Classifier: Topic :: Software Development :: Libraries :: Python Modules
Classifier: Topic :: Text Processing
Requires-Dist: requests (>=2.2.0)
Requires-Dist: pygments
